{
  "background": {
    "$value": "{white.base}",
    "$type": "color"
  },
  "foreground": {
    "$value": "{black.a900}",
    "$type": "color"
  },
  "background-hover": {
    "$value": "{gray.50}",
    "$type": "color"
  },
  "background-hover-alpha": {
    "$value": "{gray.a100}",
    "$type": "color"
  },
  "background-active": {
    "$value": "{gray.100}",
    "$type": "color"
  },
  "muted": {
    "$value": "{gray.50}",
    "$type": "color"
  },
  "muted-foreground": {
    "$value": "{black.a600}",
    "$type": "color",
    "$description": "It’s a gray that softens contrast so primary content stands forward."
  },
  "muted-foreground-subtle": {
    "$value": "{black.a500}",
    "$type": "color",
    "$description": "Tertiary text tier below muted-foreground — helper text, captions, divider labels."
  },
  "disabled": {
    "$value": "{gray.50}",
    "$type": "color"
  },
  "disabled-foreground": {
    "$value": "{gray.400}",
    "$type": "color"
  },
  "container": {
    "$value": "{white.base}",
    "$type": "color"
  },
  "container-foreground": {
    "$value": "{gray.950}",
    "$type": "color"
  },
  "container-hover": {
    "$value": "{gray.50}",
    "$type": "color"
  },
  "container-active": {
    "$value": "{gray.100}",
    "$type": "color"
  },
  "popover": {
    "$value": "{white.base}",
    "$type": "color"
  },
  "popover-foreground": {
    "$value": "{gray.950}",
    "$type": "color"
  },
  "popover-hover": {
    "$value": "{gray.50}",
    "$type": "color"
  },
  "popover-active": {
    "$value": "{gray.50}",
    "$type": "color"
  },
  "popover-alpha": {
    "$value": "{white.a900}",
    "$type": "color"
  },
  "popover-backdrop": {
    "$value": "{gray.a900}",
    "$type": "color"
  },
  "control-background": {
    "$value": "{gray.100}",
    "$type": "color"
  },
  "control-background-hover": {
    "$value": "{gray.200}",
    "$type": "color"
  },
  "control-thumb": {
    "$value": "{white.base}",
    "$type": "color"
  },
  "nav-background": {
    "$value": "{gray.100}",
    "$type": "color"
  },
  "nav-foreground": {
    "$value": "{gray.900}",
    "$type": "color"
  },
  "nav-muted-foreground": {
    "$value": "{gray.600}",
    "$type": "color"
  },
  "nav-item-hover": {
    "$value": "{gray.200}",
    "$type": "color"
  },
  "nav-item-active": {
    "$value": "{gray.200}",
    "$type": "color"
  },
  "nav-border": {
    "$value": "{gray.200}",
    "$type": "color"
  },
  "overlay": {
    "$value": "{gray.a700}",
    "$type": "color"
  },
  "border": {
    "default": {
      "$value": "{black.a200}",
      "$type": "color"
    },
    "default-alpha": {
      "$value": "{gray.a200}",
      "$type": "color"
    },
    "active": {
      "$value": "{gray.400}",
      "$type": "color"
    },
    "disabled": {
      "$value": "{black.a200}",
      "$type": "color"
    },
    "warning": {
      "$value": "{orange.200}",
      "$type": "color"
    },
    "warning-active": {
      "$value": "{orange.400}",
      "$type": "color"
    },
    "success": {
      "$value": "{green.200}",
      "$type": "color"
    },
    "success-active": {
      "$value": "{green.400}",
      "$type": "color"
    },
    "error": {
      "$value": "{red.200}",
      "$type": "color"
    },
    "error-active": {
      "$value": "{red.400}",
      "$type": "color"
    },
    "information": {
      "$value": "{blue.200}",
      "$type": "color"
    },
    "information-active": {
      "$value": "{blue.400}",
      "$type": "color"
    }
  },
  "error": {
    "background": {
      "$value": "{red.600}",
      "$type": "color"
    },
    "foreground": {
      "$value": "{white.base}",
      "$type": "color"
    },
    "background-hover": {
      "$value": "{red.700}",
      "$type": "color"
    },
    "background-active": {
      "$value": "{red.800}",
      "$type": "color"
    },
    "disabled": {
      "$value": "{red.300}",
      "$type": "color"
    },
    "subtle": {
      "$value": "{red.50}",
      "$type": "color"
    },
    "subtle-foreground": {
      "$value": "{red.600}",
      "$type": "color"
    },
    "subtle-hover": {
      "$value": "{red.100}",
      "$type": "color"
    },
    "subtle-active": {
      "$value": "{red.200}",
      "$type": "color"
    }
  },
  "success": {
    "background": {
      "$value": "{green.600}",
      "$type": "color"
    },
    "foreground": {
      "$value": "{white.base}",
      "$type": "color"
    },
    "background-hover": {
      "$value": "{green.700}",
      "$type": "color"
    },
    "background-active": {
      "$value": "{green.800}",
      "$type": "color"
    },
    "disabled": {
      "$value": "{green.300}",
      "$type": "color"
    },
    "subtle": {
      "$value": "{green.50}",
      "$type": "color"
    },
    "subtle-foreground": {
      "$value": "{green.700}",
      "$type": "color"
    },
    "subtle-hover": {
      "$value": "{green.100}",
      "$type": "color"
    },
    "subtle-active": {
      "$value": "{green.200}",
      "$type": "color"
    }
  },
  "information": {
    "background": {
      "$value": "{blue.600}",
      "$type": "color"
    },
    "foreground": {
      "$value": "{white.base}",
      "$type": "color"
    },
    "background-hover": {
      "$value": "{blue.700}",
      "$type": "color"
    },
    "background-active": {
      "$value": "{blue.800}",
      "$type": "color"
    },
    "disabled": {
      "$value": "{blue.300}",
      "$type": "color"
    },
    "subtle": {
      "$value": "{blue.50}",
      "$type": "color"
    },
    "subtle-foreground": {
      "$value": "{blue.600}",
      "$type": "color"
    },
    "subtle-hover": {
      "$value": "{blue.100}",
      "$type": "color"
    },
    "subtle-active": {
      "$value": "{blue.200}",
      "$type": "color"
    }
  },
  "warning": {
    "background": {
      "$value": "{orange.600}",
      "$type": "color"
    },
    "foreground": {
      "$value": "{white.base}",
      "$type": "color"
    },
    "background-hover": {
      "$value": "{orange.700}",
      "$type": "color"
    },
    "background-active": {
      "$value": "{orange.800}",
      "$type": "color"
    },
    "disabled": {
      "$value": "{orange.300}",
      "$type": "color"
    },
    "subtle": {
      "$value": "{orange.50}",
      "$type": "color"
    },
    "subtle-foreground": {
      "$value": "{orange.600}",
      "$type": "color"
    },
    "subtle-hover": {
      "$value": "{orange.100}",
      "$type": "color"
    },
    "subtle-active": {
      "$value": "{orange.200}",
      "$type": "color"
    }
  }
}
